odoo/addons/account_due_list_payment_mode/README.rst
odoo/addons/account_due_list_payment_mode/__init__.py
odoo/addons/account_due_list_payment_mode/__manifest__.py
odoo/addons/account_due_list_payment_mode/i18n/account_due_list_payment_mode.pot
odoo/addons/account_due_list_payment_mode/i18n/de.po
odoo/addons/account_due_list_payment_mode/i18n/es.po
odoo/addons/account_due_list_payment_mode/i18n/es_AR.po
odoo/addons/account_due_list_payment_mode/i18n/it.po
odoo/addons/account_due_list_payment_mode/i18n/pt_BR.po
odoo/addons/account_due_list_payment_mode/readme/CONFIGURE.rst
odoo/addons/account_due_list_payment_mode/readme/CONTRIBUTORS.rst
odoo/addons/account_due_list_payment_mode/readme/DESCRIPTION.rst
odoo/addons/account_due_list_payment_mode/readme/INSTALL.rst
odoo/addons/account_due_list_payment_mode/readme/USAGE.rst
odoo/addons/account_due_list_payment_mode/static/description/icon.png
odoo/addons/account_due_list_payment_mode/static/description/index.html
odoo/addons/account_due_list_payment_mode/views/payment_view.xml
odoo14_addon_account_due_list_payment_mode-14.0.1.0.1.dev9.dist-info/METADATA
odoo14_addon_account_due_list_payment_mode-14.0.1.0.1.dev9.dist-info/WHEEL
odoo14_addon_account_due_list_payment_mode-14.0.1.0.1.dev9.dist-info/top_level.txt
odoo14_addon_account_due_list_payment_mode-14.0.1.0.1.dev9.dist-info/RECORD
